{"/*":["X-Frame-Options: DENY","X-XSS-Protection: 1; mode=block","X-Content-Type-Options: nosniff","Referrer-Policy: same-origin"],"/styles.47e227a432857fe0464f.css":["Cache-Control: public, max-age=31536000, immutable"],"/commons-4229773709d1684763e0.js":["Cache-Control: public, max-age=31536000, immutable"],"/component---src-templates-blog-post-tsx-cffc0d75d3e219754ee4.js":["Cache-Control: public, max-age=31536000, immutable"],"/component---src-templates-etc-tsx-bdb7b36269255ccee0bd.js":["Cache-Control: public, max-age=31536000, immutable"],"/component---src-templates-year-tsx-722f9c28dbeac162c801.js":["Cache-Control: public, max-age=31536000, immutable"],"/component---src-templates-organization-tsx-32af452985cce2651fa3.js":["Cache-Control: public, max-age=31536000, immutable"],"/component---src-templates-level-tsx-825d7ff053fb0275324b.js":["Cache-Control: public, max-age=31536000, immutable"],"/component---src-templates-subject-tsx-5b5a201b1f593dd6f57b.js":["Cache-Control: public, max-age=31536000, immutable"],"/component---src-pages-404-tsx-63c569cec9a5085651f9.js":["Cache-Control: public, max-age=31536000, immutable"],"/component---src-pages-etc-tsx-f4141b91c17644268ec1.js":["Cache-Control: public, max-age=31536000, immutable"],"/component---src-pages-index-tsx-571067566ee9b751c0da.js":["Cache-Control: public, max-age=31536000, immutable"],"/component---src-pages-level-tsx-6d1b1c16161c19e6c046.js":["Cache-Control: public, max-age=31536000, immutable"],"/component---src-pages-org-tsx-44be0d7f2b5f3f1c823f.js":["Cache-Control: public, max-age=31536000, immutable"],"/component---src-pages-subject-tsx-27ad132da74c3c1f160e.js":["Cache-Control: public, max-age=31536000, immutable"],"/component---src-pages-year-tsx-02e4ebaeb5fe48735458.js":["Cache-Control: public, max-age=31536000, immutable"],"/webpack-runtime-550d9c70ac0e254df46f.js":["Cache-Control: public, max-age=31536000, immutable"],"/framework-c8eaec10e45cecbdf79e.js":["Cache-Control: public, max-age=31536000, immutable"],"/app-1af3f4ffdc27ce697953.js":["Cache-Control: public, max-age=31536000, immutable"],"/static/*":["Cache-Control: public, max-age=31536000, immutable"],"/sw.js":["Cache-Control: public, max-age=0, must-revalidate"],"/2021-9-seoul-ee/":["Link: </webpack-runtime-550d9c70ac0e254df46f.js>; rel=preload; as=script; nopush","Link: </framework-c8eaec10e45cecbdf79e.js>; rel=preload; as=script; nopush","Link: </app-1af3f4ffdc27ce697953.js>; rel=preload; as=script; nopush","Link: </commons-4229773709d1684763e0.js>; rel=preload; as=script; nopush","Link: </component---src-templates-blog-post-tsx-cffc0d75d3e219754ee4.js>; rel=preload; as=script; nopush","Link: </page-data/app-data.json>; rel=preload; as=fetch; crossorigin; nopush","Link: </page-data/2021-9-seoul-ee/page-data.json>; rel=preload; as=fetch; crossorigin; nopush"],"/2022-7-national-comm/":["Link: </webpack-runtime-550d9c70ac0e254df46f.js>; rel=preload; as=script; nopush","Link: </framework-c8eaec10e45cecbdf79e.js>; rel=preload; as=script; nopush","Link: </app-1af3f4ffdc27ce697953.js>; rel=preload; as=script; nopush","Link: </commons-4229773709d1684763e0.js>; rel=preload; as=script; nopush","Link: </component---src-templates-blog-post-tsx-cffc0d75d3e219754ee4.js>; rel=preload; as=script; nopush","Link: </page-data/app-data.json>; rel=preload; as=fetch; crossorigin; nopush","Link: </page-data/2022-7-national-comm/page-data.json>; rel=preload; as=fetch; crossorigin; nopush"],"/2022-7-national-ct/":["Link: </webpack-runtime-550d9c70ac0e254df46f.js>; rel=preload; as=script; nopush","Link: </framework-c8eaec10e45cecbdf79e.js>; rel=preload; as=script; nopush","Link: </app-1af3f4ffdc27ce697953.js>; rel=preload; as=script; nopush","Link: </commons-4229773709d1684763e0.js>; rel=preload; as=script; nopush","Link: </component---src-templates-blog-post-tsx-cffc0d75d3e219754ee4.js>; rel=preload; as=script; nopush","Link: </page-data/app-data.json>; rel=preload; as=fetch; crossorigin; nopush","Link: </page-data/2022-7-national-ct/page-data.json>; rel=preload; as=fetch; crossorigin; nopush"],"/2022-7-national-em/":["Link: </webpack-runtime-550d9c70ac0e254df46f.js>; rel=preload; as=script; nopush","Link: </framework-c8eaec10e45cecbdf79e.js>; rel=preload; as=script; nopush","Link: </app-1af3f4ffdc27ce697953.js>; rel=preload; as=script; nopush","Link: </commons-4229773709d1684763e0.js>; rel=preload; as=script; nopush","Link: </component---src-templates-blog-post-tsx-cffc0d75d3e219754ee4.js>; rel=preload; as=script; nopush","Link: </page-data/app-data.json>; rel=preload; as=fetch; crossorigin; nopush","Link: </page-data/2022-7-national-em/page-data.json>; rel=preload; as=fetch; crossorigin; nopush"],"/2022-7-mil-ec/":["Link: </webpack-runtime-550d9c70ac0e254df46f.js>; rel=preload; as=script; nopush","Link: </framework-c8eaec10e45cecbdf79e.js>; rel=preload; as=script; nopush","Link: </app-1af3f4ffdc27ce697953.js>; rel=preload; as=script; nopush","Link: </commons-4229773709d1684763e0.js>; rel=preload; as=script; nopush","Link: </component---src-templates-blog-post-tsx-cffc0d75d3e219754ee4.js>; rel=preload; as=script; nopush","Link: </page-data/app-data.json>; rel=preload; as=fetch; crossorigin; nopush","Link: </page-data/2022-7-mil-ec/page-data.json>; rel=preload; as=fetch; crossorigin; nopush"],"/2022-9-national-ee/":["Link: </webpack-runtime-550d9c70ac0e254df46f.js>; rel=preload; as=script; nopush","Link: </framework-c8eaec10e45cecbdf79e.js>; rel=preload; as=script; nopush","Link: </app-1af3f4ffdc27ce697953.js>; rel=preload; as=script; nopush","Link: </commons-4229773709d1684763e0.js>; rel=preload; as=script; nopush","Link: </component---src-templates-blog-post-tsx-cffc0d75d3e219754ee4.js>; rel=preload; as=script; nopush","Link: </page-data/app-data.json>; rel=preload; as=fetch; crossorigin; nopush","Link: </page-data/2022-9-national-ee/page-data.json>; rel=preload; as=fetch; crossorigin; nopush"],"/2022-9-national-we/":["Link: </webpack-runtime-550d9c70ac0e254df46f.js>; rel=preload; as=script; nopush","Link: </framework-c8eaec10e45cecbdf79e.js>; rel=preload; as=script; nopush","Link: </app-1af3f4ffdc27ce697953.js>; rel=preload; as=script; nopush","Link: </commons-4229773709d1684763e0.js>; rel=preload; as=script; nopush","Link: </component---src-templates-blog-post-tsx-cffc0d75d3e219754ee4.js>; rel=preload; as=script; nopush","Link: </page-data/app-data.json>; rel=preload; as=fetch; crossorigin; nopush","Link: </page-data/2022-9-national-we/page-data.json>; rel=preload; as=fetch; crossorigin; nopush"],"/2022-7-national-ec/":["Link: </webpack-runtime-550d9c70ac0e254df46f.js>; rel=preload; as=script; nopush","Link: </framework-c8eaec10e45cecbdf79e.js>; rel=preload; as=script; nopush","Link: </app-1af3f4ffdc27ce697953.js>; rel=preload; as=script; nopush","Link: </commons-4229773709d1684763e0.js>; rel=preload; as=script; nopush","Link: </component---src-templates-blog-post-tsx-cffc0d75d3e219754ee4.js>; rel=preload; as=script; nopush","Link: </page-data/app-data.json>; rel=preload; as=fetch; crossorigin; nopush","Link: </page-data/2022-7-national-ec/page-data.json>; rel=preload; as=fetch; crossorigin; nopush"],"/2023-9-national-ee/":["Link: </webpack-runtime-550d9c70ac0e254df46f.js>; rel=preload; as=script; nopush","Link: </framework-c8eaec10e45cecbdf79e.js>; rel=preload; as=script; nopush","Link: </app-1af3f4ffdc27ce697953.js>; rel=preload; as=script; nopush","Link: </commons-4229773709d1684763e0.js>; rel=preload; as=script; nopush","Link: </component---src-templates-blog-post-tsx-cffc0d75d3e219754ee4.js>; rel=preload; as=script; nopush","Link: </page-data/app-data.json>; rel=preload; as=fetch; crossorigin; nopush","Link: </page-data/2023-9-national-ee/page-data.json>; rel=preload; as=fetch; crossorigin; nopush"],"/2022-9-province-ct/":["Link: </webpack-runtime-550d9c70ac0e254df46f.js>; rel=preload; as=script; nopush","Link: </framework-c8eaec10e45cecbdf79e.js>; rel=preload; as=script; nopush","Link: </app-1af3f4ffdc27ce697953.js>; rel=preload; as=script; nopush","Link: </commons-4229773709d1684763e0.js>; rel=preload; as=script; nopush","Link: </component---src-templates-blog-post-tsx-cffc0d75d3e219754ee4.js>; rel=preload; as=script; nopush","Link: </page-data/app-data.json>; rel=preload; as=fetch; crossorigin; nopush","Link: </page-data/2022-9-province-ct/page-data.json>; rel=preload; as=fetch; crossorigin; nopush"],"/2023-9-national-we/":["Link: </webpack-runtime-550d9c70ac0e254df46f.js>; rel=preload; as=script; nopush","Link: </framework-c8eaec10e45cecbdf79e.js>; rel=preload; as=script; nopush","Link: </app-1af3f4ffdc27ce697953.js>; rel=preload; as=script; nopush","Link: </commons-4229773709d1684763e0.js>; rel=preload; as=script; nopush","Link: </component---src-templates-blog-post-tsx-cffc0d75d3e219754ee4.js>; rel=preload; as=script; nopush","Link: </page-data/app-data.json>; rel=preload; as=fetch; crossorigin; nopush","Link: </page-data/2023-9-national-we/page-data.json>; rel=preload; as=fetch; crossorigin; nopush"],"/2022-9-province-ec/":["Link: </webpack-runtime-550d9c70ac0e254df46f.js>; rel=preload; as=script; nopush","Link: </framework-c8eaec10e45cecbdf79e.js>; rel=preload; as=script; nopush","Link: </app-1af3f4ffdc27ce697953.js>; rel=preload; as=script; nopush","Link: </commons-4229773709d1684763e0.js>; rel=preload; as=script; nopush","Link: </component---src-templates-blog-post-tsx-cffc0d75d3e219754ee4.js>; rel=preload; as=script; nopush","Link: </page-data/app-data.json>; rel=preload; as=fetch; crossorigin; nopush","Link: </page-data/2022-9-province-ec/page-data.json>; rel=preload; as=fetch; crossorigin; nopush"],"/introducing_myself/":["Link: </webpack-runtime-550d9c70ac0e254df46f.js>; rel=preload; as=script; nopush","Link: </framework-c8eaec10e45cecbdf79e.js>; rel=preload; as=script; nopush","Link: </app-1af3f4ffdc27ce697953.js>; rel=preload; as=script; nopush","Link: </commons-4229773709d1684763e0.js>; rel=preload; as=script; nopush","Link: </component---src-templates-blog-post-tsx-cffc0d75d3e219754ee4.js>; rel=preload; as=script; nopush","Link: </page-data/app-data.json>; rel=preload; as=fetch; crossorigin; nopush","Link: </page-data/introducing_myself/page-data.json>; rel=preload; as=fetch; crossorigin; nopush"],"/Notice/":["Link: </webpack-runtime-550d9c70ac0e254df46f.js>; rel=preload; as=script; nopush","Link: </framework-c8eaec10e45cecbdf79e.js>; rel=preload; as=script; nopush","Link: </app-1af3f4ffdc27ce697953.js>; rel=preload; as=script; nopush","Link: </commons-4229773709d1684763e0.js>; rel=preload; as=script; nopush","Link: </component---src-templates-blog-post-tsx-cffc0d75d3e219754ee4.js>; rel=preload; as=script; nopush","Link: </page-data/app-data.json>; rel=preload; as=fetch; crossorigin; nopush","Link: </page-data/Notice/page-data.json>; rel=preload; as=fetch; crossorigin; nopush"],"/License/":["Link: </webpack-runtime-550d9c70ac0e254df46f.js>; rel=preload; as=script; nopush","Link: </framework-c8eaec10e45cecbdf79e.js>; rel=preload; as=script; nopush","Link: </app-1af3f4ffdc27ce697953.js>; rel=preload; as=script; nopush","Link: </commons-4229773709d1684763e0.js>; rel=preload; as=script; nopush","Link: </component---src-templates-blog-post-tsx-cffc0d75d3e219754ee4.js>; rel=preload; as=script; nopush","Link: </page-data/app-data.json>; rel=preload; as=fetch; crossorigin; nopush","Link: </page-data/License/page-data.json>; rel=preload; as=fetch; crossorigin; nopush"],"/pdf/":["Link: </webpack-runtime-550d9c70ac0e254df46f.js>; rel=preload; as=script; nopush","Link: </framework-c8eaec10e45cecbdf79e.js>; rel=preload; as=script; nopush","Link: </app-1af3f4ffdc27ce697953.js>; rel=preload; as=script; nopush","Link: </commons-4229773709d1684763e0.js>; rel=preload; as=script; nopush","Link: </component---src-templates-blog-post-tsx-cffc0d75d3e219754ee4.js>; rel=preload; as=script; nopush","Link: </page-data/app-data.json>; rel=preload; as=fetch; crossorigin; nopush","Link: </page-data/pdf/page-data.json>; rel=preload; as=fetch; crossorigin; nopush"],"/etc/안내":["Link: </webpack-runtime-550d9c70ac0e254df46f.js>; rel=preload; as=script; nopush","Link: </framework-c8eaec10e45cecbdf79e.js>; rel=preload; as=script; nopush","Link: </app-1af3f4ffdc27ce697953.js>; rel=preload; as=script; nopush","Link: </commons-4229773709d1684763e0.js>; rel=preload; as=script; nopush","Link: </component---src-templates-etc-tsx-bdb7b36269255ccee0bd.js>; rel=preload; as=script; nopush","Link: </page-data/app-data.json>; rel=preload; as=fetch; crossorigin; nopush","Link: </page-data/etc/안내/page-data.json>; rel=preload; as=fetch; crossorigin; nopush"],"/year/2023년":["Link: </webpack-runtime-550d9c70ac0e254df46f.js>; rel=preload; as=script; nopush","Link: </framework-c8eaec10e45cecbdf79e.js>; rel=preload; as=script; nopush","Link: </app-1af3f4ffdc27ce697953.js>; rel=preload; as=script; nopush","Link: </commons-4229773709d1684763e0.js>; rel=preload; as=script; nopush","Link: </component---src-templates-year-tsx-722f9c28dbeac162c801.js>; rel=preload; as=script; nopush","Link: </page-data/app-data.json>; rel=preload; as=fetch; crossorigin; nopush","Link: </page-data/year/2023년/page-data.json>; rel=preload; as=fetch; crossorigin; nopush"],"/year/2022년":["Link: </webpack-runtime-550d9c70ac0e254df46f.js>; rel=preload; as=script; nopush","Link: </framework-c8eaec10e45cecbdf79e.js>; rel=preload; as=script; nopush","Link: </app-1af3f4ffdc27ce697953.js>; rel=preload; as=script; nopush","Link: </commons-4229773709d1684763e0.js>; rel=preload; as=script; nopush","Link: </component---src-templates-year-tsx-722f9c28dbeac162c801.js>; rel=preload; as=script; nopush","Link: </page-data/app-data.json>; rel=preload; as=fetch; crossorigin; nopush","Link: </page-data/year/2022년/page-data.json>; rel=preload; as=fetch; crossorigin; nopush"],"/org/서울시":["Link: </webpack-runtime-550d9c70ac0e254df46f.js>; rel=preload; as=script; nopush","Link: </framework-c8eaec10e45cecbdf79e.js>; rel=preload; as=script; nopush","Link: </app-1af3f4ffdc27ce697953.js>; rel=preload; as=script; nopush","Link: </commons-4229773709d1684763e0.js>; rel=preload; as=script; nopush","Link: </component---src-templates-organization-tsx-32af452985cce2651fa3.js>; rel=preload; as=script; nopush","Link: </page-data/app-data.json>; rel=preload; as=fetch; crossorigin; nopush","Link: </page-data/org/서울시/page-data.json>; rel=preload; as=fetch; crossorigin; nopush"],"/org/국가직":["Link: </webpack-runtime-550d9c70ac0e254df46f.js>; rel=preload; as=script; nopush","Link: </framework-c8eaec10e45cecbdf79e.js>; rel=preload; as=script; nopush","Link: </app-1af3f4ffdc27ce697953.js>; rel=preload; as=script; nopush","Link: </commons-4229773709d1684763e0.js>; rel=preload; as=script; nopush","Link: </component---src-templates-organization-tsx-32af452985cce2651fa3.js>; rel=preload; as=script; nopush","Link: </page-data/app-data.json>; rel=preload; as=fetch; crossorigin; nopush","Link: </page-data/org/국가직/page-data.json>; rel=preload; as=fetch; crossorigin; nopush"],"/org/군무원":["Link: </webpack-runtime-550d9c70ac0e254df46f.js>; rel=preload; as=script; nopush","Link: </framework-c8eaec10e45cecbdf79e.js>; rel=preload; as=script; nopush","Link: </app-1af3f4ffdc27ce697953.js>; rel=preload; as=script; nopush","Link: </commons-4229773709d1684763e0.js>; rel=preload; as=script; nopush","Link: </component---src-templates-organization-tsx-32af452985cce2651fa3.js>; rel=preload; as=script; nopush","Link: </page-data/app-data.json>; rel=preload; as=fetch; crossorigin; nopush","Link: </page-data/org/군무원/page-data.json>; rel=preload; as=fetch; crossorigin; nopush"],"/org/지방직":["Link: </webpack-runtime-550d9c70ac0e254df46f.js>; rel=preload; as=script; nopush","Link: </framework-c8eaec10e45cecbdf79e.js>; rel=preload; as=script; nopush","Link: </app-1af3f4ffdc27ce697953.js>; rel=preload; as=script; nopush","Link: </commons-4229773709d1684763e0.js>; rel=preload; as=script; nopush","Link: </component---src-templates-organization-tsx-32af452985cce2651fa3.js>; rel=preload; as=script; nopush","Link: </page-data/app-data.json>; rel=preload; as=fetch; crossorigin; nopush","Link: </page-data/org/지방직/page-data.json>; rel=preload; as=fetch; crossorigin; nopush"],"/level/9급":["Link: </webpack-runtime-550d9c70ac0e254df46f.js>; rel=preload; as=script; nopush","Link: </framework-c8eaec10e45cecbdf79e.js>; rel=preload; as=script; nopush","Link: </app-1af3f4ffdc27ce697953.js>; rel=preload; as=script; nopush","Link: </commons-4229773709d1684763e0.js>; rel=preload; as=script; nopush","Link: </component---src-templates-level-tsx-825d7ff053fb0275324b.js>; rel=preload; as=script; nopush","Link: </page-data/app-data.json>; rel=preload; as=fetch; crossorigin; nopush","Link: </page-data/level/9급/page-data.json>; rel=preload; as=fetch; crossorigin; nopush"],"/level/7급":["Link: </webpack-runtime-550d9c70ac0e254df46f.js>; rel=preload; as=script; nopush","Link: </framework-c8eaec10e45cecbdf79e.js>; rel=preload; as=script; nopush","Link: </app-1af3f4ffdc27ce697953.js>; rel=preload; as=script; nopush","Link: </commons-4229773709d1684763e0.js>; rel=preload; as=script; nopush","Link: </component---src-templates-level-tsx-825d7ff053fb0275324b.js>; rel=preload; as=script; nopush","Link: </page-data/app-data.json>; rel=preload; as=fetch; crossorigin; nopush","Link: </page-data/level/7급/page-data.json>; rel=preload; as=fetch; crossorigin; nopush"],"/subject/전자공학개론":["Link: </webpack-runtime-550d9c70ac0e254df46f.js>; rel=preload; as=script; nopush","Link: </framework-c8eaec10e45cecbdf79e.js>; rel=preload; as=script; nopush","Link: </app-1af3f4ffdc27ce697953.js>; rel=preload; as=script; nopush","Link: </commons-4229773709d1684763e0.js>; rel=preload; as=script; nopush","Link: </component---src-templates-subject-tsx-5b5a201b1f593dd6f57b.js>; rel=preload; as=script; nopush","Link: </page-data/app-data.json>; rel=preload; as=fetch; crossorigin; nopush","Link: </page-data/subject/전자공학개론/page-data.json>; rel=preload; as=fetch; crossorigin; nopush"],"/subject/통신이론":["Link: </webpack-runtime-550d9c70ac0e254df46f.js>; rel=preload; as=script; nopush","Link: </framework-c8eaec10e45cecbdf79e.js>; rel=preload; as=script; nopush","Link: </app-1af3f4ffdc27ce697953.js>; rel=preload; as=script; nopush","Link: </commons-4229773709d1684763e0.js>; rel=preload; as=script; nopush","Link: </component---src-templates-subject-tsx-5b5a201b1f593dd6f57b.js>; rel=preload; as=script; nopush","Link: </page-data/app-data.json>; rel=preload; as=fetch; crossorigin; nopush","Link: </page-data/subject/통신이론/page-data.json>; rel=preload; as=fetch; crossorigin; nopush"],"/subject/회로이론":["Link: </webpack-runtime-550d9c70ac0e254df46f.js>; rel=preload; as=script; nopush","Link: </framework-c8eaec10e45cecbdf79e.js>; rel=preload; as=script; nopush","Link: </app-1af3f4ffdc27ce697953.js>; rel=preload; as=script; nopush","Link: </commons-4229773709d1684763e0.js>; rel=preload; as=script; nopush","Link: </component---src-templates-subject-tsx-5b5a201b1f593dd6f57b.js>; rel=preload; as=script; nopush","Link: </page-data/app-data.json>; rel=preload; as=fetch; crossorigin; nopush","Link: </page-data/subject/회로이론/page-data.json>; rel=preload; as=fetch; crossorigin; nopush"],"/subject/전기자기학":["Link: </webpack-runtime-550d9c70ac0e254df46f.js>; rel=preload; as=script; nopush","Link: </framework-c8eaec10e45cecbdf79e.js>; rel=preload; as=script; nopush","Link: </app-1af3f4ffdc27ce697953.js>; rel=preload; as=script; nopush","Link: </commons-4229773709d1684763e0.js>; rel=preload; as=script; nopush","Link: </component---src-templates-subject-tsx-5b5a201b1f593dd6f57b.js>; rel=preload; as=script; nopush","Link: </page-data/app-data.json>; rel=preload; as=fetch; crossorigin; nopush","Link: </page-data/subject/전기자기학/page-data.json>; rel=preload; as=fetch; crossorigin; nopush"],"/subject/전자회로":["Link: </webpack-runtime-550d9c70ac0e254df46f.js>; rel=preload; as=script; nopush","Link: </framework-c8eaec10e45cecbdf79e.js>; rel=preload; as=script; nopush","Link: </app-1af3f4ffdc27ce697953.js>; rel=preload; as=script; nopush","Link: </commons-4229773709d1684763e0.js>; rel=preload; as=script; nopush","Link: </component---src-templates-subject-tsx-5b5a201b1f593dd6f57b.js>; rel=preload; as=script; nopush","Link: </page-data/app-data.json>; rel=preload; as=fetch; crossorigin; nopush","Link: </page-data/subject/전자회로/page-data.json>; rel=preload; as=fetch; crossorigin; nopush"],"/subject/무선공학개론":["Link: </webpack-runtime-550d9c70ac0e254df46f.js>; rel=preload; as=script; nopush","Link: </framework-c8eaec10e45cecbdf79e.js>; rel=preload; as=script; nopush","Link: </app-1af3f4ffdc27ce697953.js>; rel=preload; as=script; nopush","Link: </commons-4229773709d1684763e0.js>; rel=preload; as=script; nopush","Link: </component---src-templates-subject-tsx-5b5a201b1f593dd6f57b.js>; rel=preload; as=script; nopush","Link: </page-data/app-data.json>; rel=preload; as=fetch; crossorigin; nopush","Link: </page-data/subject/무선공학개론/page-data.json>; rel=preload; as=fetch; crossorigin; nopush"],"/404/":["Link: </webpack-runtime-550d9c70ac0e254df46f.js>; rel=preload; as=script; nopush","Link: </framework-c8eaec10e45cecbdf79e.js>; rel=preload; as=script; nopush","Link: </app-1af3f4ffdc27ce697953.js>; rel=preload; as=script; nopush","Link: </commons-4229773709d1684763e0.js>; rel=preload; as=script; nopush","Link: </component---src-pages-404-tsx-63c569cec9a5085651f9.js>; rel=preload; as=script; nopush","Link: </page-data/app-data.json>; rel=preload; as=fetch; crossorigin; nopush","Link: </page-data/404/page-data.json>; rel=preload; as=fetch; crossorigin; nopush"],"/404.html":["Link: </webpack-runtime-550d9c70ac0e254df46f.js>; rel=preload; as=script; nopush","Link: </framework-c8eaec10e45cecbdf79e.js>; rel=preload; as=script; nopush","Link: </app-1af3f4ffdc27ce697953.js>; rel=preload; as=script; nopush","Link: </commons-4229773709d1684763e0.js>; rel=preload; as=script; nopush","Link: </component---src-pages-404-tsx-63c569cec9a5085651f9.js>; rel=preload; as=script; nopush","Link: </page-data/app-data.json>; rel=preload; as=fetch; crossorigin; nopush","Link: </page-data/404.html/page-data.json>; rel=preload; as=fetch; crossorigin; nopush"],"/etc/":["Link: </webpack-runtime-550d9c70ac0e254df46f.js>; rel=preload; as=script; nopush","Link: </framework-c8eaec10e45cecbdf79e.js>; rel=preload; as=script; nopush","Link: </app-1af3f4ffdc27ce697953.js>; rel=preload; as=script; nopush","Link: </commons-4229773709d1684763e0.js>; rel=preload; as=script; nopush","Link: </component---src-pages-etc-tsx-f4141b91c17644268ec1.js>; rel=preload; as=script; nopush","Link: </page-data/app-data.json>; rel=preload; as=fetch; crossorigin; nopush","Link: </page-data/etc/page-data.json>; rel=preload; as=fetch; crossorigin; nopush"],"/":["Link: </webpack-runtime-550d9c70ac0e254df46f.js>; rel=preload; as=script; nopush","Link: </framework-c8eaec10e45cecbdf79e.js>; rel=preload; as=script; nopush","Link: </app-1af3f4ffdc27ce697953.js>; rel=preload; as=script; nopush","Link: </commons-4229773709d1684763e0.js>; rel=preload; as=script; nopush","Link: </component---src-pages-index-tsx-571067566ee9b751c0da.js>; rel=preload; as=script; nopush","Link: </page-data/app-data.json>; rel=preload; as=fetch; crossorigin; nopush","Link: </page-data/index/page-data.json>; rel=preload; as=fetch; crossorigin; nopush"],"/level/":["Link: </webpack-runtime-550d9c70ac0e254df46f.js>; rel=preload; as=script; nopush","Link: </framework-c8eaec10e45cecbdf79e.js>; rel=preload; as=script; nopush","Link: </app-1af3f4ffdc27ce697953.js>; rel=preload; as=script; nopush","Link: </commons-4229773709d1684763e0.js>; rel=preload; as=script; nopush","Link: </component---src-pages-level-tsx-6d1b1c16161c19e6c046.js>; rel=preload; as=script; nopush","Link: </page-data/app-data.json>; rel=preload; as=fetch; crossorigin; nopush","Link: </page-data/level/page-data.json>; rel=preload; as=fetch; crossorigin; nopush"],"/org/":["Link: </webpack-runtime-550d9c70ac0e254df46f.js>; rel=preload; as=script; nopush","Link: </framework-c8eaec10e45cecbdf79e.js>; rel=preload; as=script; nopush","Link: </app-1af3f4ffdc27ce697953.js>; rel=preload; as=script; nopush","Link: </commons-4229773709d1684763e0.js>; rel=preload; as=script; nopush","Link: </component---src-pages-org-tsx-44be0d7f2b5f3f1c823f.js>; rel=preload; as=script; nopush","Link: </page-data/app-data.json>; rel=preload; as=fetch; crossorigin; nopush","Link: </page-data/org/page-data.json>; rel=preload; as=fetch; crossorigin; nopush"],"/subject/":["Link: </webpack-runtime-550d9c70ac0e254df46f.js>; rel=preload; as=script; nopush","Link: </framework-c8eaec10e45cecbdf79e.js>; rel=preload; as=script; nopush","Link: </app-1af3f4ffdc27ce697953.js>; rel=preload; as=script; nopush","Link: </commons-4229773709d1684763e0.js>; rel=preload; as=script; nopush","Link: </component---src-pages-subject-tsx-27ad132da74c3c1f160e.js>; rel=preload; as=script; nopush","Link: </page-data/app-data.json>; rel=preload; as=fetch; crossorigin; nopush","Link: </page-data/subject/page-data.json>; rel=preload; as=fetch; crossorigin; nopush"],"/year/":["Link: </webpack-runtime-550d9c70ac0e254df46f.js>; rel=preload; as=script; nopush","Link: </framework-c8eaec10e45cecbdf79e.js>; rel=preload; as=script; nopush","Link: </app-1af3f4ffdc27ce697953.js>; rel=preload; as=script; nopush","Link: </commons-4229773709d1684763e0.js>; rel=preload; as=script; nopush","Link: </component---src-pages-year-tsx-02e4ebaeb5fe48735458.js>; rel=preload; as=script; nopush","Link: </page-data/app-data.json>; rel=preload; as=fetch; crossorigin; nopush","Link: </page-data/year/page-data.json>; rel=preload; as=fetch; crossorigin; nopush"],"/2021-7-national-comm/":["Link: </webpack-runtime-550d9c70ac0e254df46f.js>; rel=preload; as=script; nopush","Link: </framework-c8eaec10e45cecbdf79e.js>; rel=preload; as=script; nopush","Link: </app-1af3f4ffdc27ce697953.js>; rel=preload; as=script; nopush","Link: </commons-4229773709d1684763e0.js>; rel=preload; as=script; nopush","Link: </component---src-templates-blog-post-tsx-cffc0d75d3e219754ee4.js>; rel=preload; as=script; nopush","Link: </page-data/app-data.json>; rel=preload; as=fetch; crossorigin; nopush","Link: </page-data/2021-7-national-comm/page-data.json>; rel=preload; as=fetch; crossorigin; nopush"],"/year/2021년":["Link: </webpack-runtime-550d9c70ac0e254df46f.js>; rel=preload; as=script; nopush","Link: </framework-c8eaec10e45cecbdf79e.js>; rel=preload; as=script; nopush","Link: </app-1af3f4ffdc27ce697953.js>; rel=preload; as=script; nopush","Link: </commons-4229773709d1684763e0.js>; rel=preload; as=script; nopush","Link: </component---src-templates-year-tsx-722f9c28dbeac162c801.js>; rel=preload; as=script; nopush","Link: </page-data/app-data.json>; rel=preload; as=fetch; crossorigin; nopush","Link: </page-data/year/2021년/page-data.json>; rel=preload; as=fetch; crossorigin; nopush"],"/2020-7-seoul-comm/":["Link: </webpack-runtime-550d9c70ac0e254df46f.js>; rel=preload; as=script; nopush","Link: </framework-c8eaec10e45cecbdf79e.js>; rel=preload; as=script; nopush","Link: </app-1af3f4ffdc27ce697953.js>; rel=preload; as=script; nopush","Link: </commons-4229773709d1684763e0.js>; rel=preload; as=script; nopush","Link: </component---src-templates-blog-post-tsx-cffc0d75d3e219754ee4.js>; rel=preload; as=script; nopush","Link: </page-data/app-data.json>; rel=preload; as=fetch; crossorigin; nopush","Link: </page-data/2020-7-seoul-comm/page-data.json>; rel=preload; as=fetch; crossorigin; nopush"],"/year/2020년":["Link: </webpack-runtime-550d9c70ac0e254df46f.js>; rel=preload; as=script; nopush","Link: </framework-c8eaec10e45cecbdf79e.js>; rel=preload; as=script; nopush","Link: </app-1af3f4ffdc27ce697953.js>; rel=preload; as=script; nopush","Link: </commons-4229773709d1684763e0.js>; rel=preload; as=script; nopush","Link: </component---src-templates-year-tsx-722f9c28dbeac162c801.js>; rel=preload; as=script; nopush","Link: </page-data/app-data.json>; rel=preload; as=fetch; crossorigin; nopush","Link: </page-data/year/2020년/page-data.json>; rel=preload; as=fetch; crossorigin; nopush"],"/2020-7-national-comm/":["Link: </webpack-runtime-550d9c70ac0e254df46f.js>; rel=preload; as=script; nopush","Link: </framework-c8eaec10e45cecbdf79e.js>; rel=preload; as=script; nopush","Link: </app-1af3f4ffdc27ce697953.js>; rel=preload; as=script; nopush","Link: </commons-4229773709d1684763e0.js>; rel=preload; as=script; nopush","Link: </component---src-templates-blog-post-tsx-cffc0d75d3e219754ee4.js>; rel=preload; as=script; nopush","Link: </page-data/app-data.json>; rel=preload; as=fetch; crossorigin; nopush","Link: </page-data/2020-7-national-comm/page-data.json>; rel=preload; as=fetch; crossorigin; nopush"],"/2019-7-seoul-comm/":["Link: </webpack-runtime-550d9c70ac0e254df46f.js>; rel=preload; as=script; nopush","Link: </framework-c8eaec10e45cecbdf79e.js>; rel=preload; as=script; nopush","Link: </app-1af3f4ffdc27ce697953.js>; rel=preload; as=script; nopush","Link: </commons-4229773709d1684763e0.js>; rel=preload; as=script; nopush","Link: </component---src-templates-blog-post-tsx-cffc0d75d3e219754ee4.js>; rel=preload; as=script; nopush","Link: </page-data/app-data.json>; rel=preload; as=fetch; crossorigin; nopush","Link: </page-data/2019-7-seoul-comm/page-data.json>; rel=preload; as=fetch; crossorigin; nopush"],"/year/2019년":["Link: </webpack-runtime-550d9c70ac0e254df46f.js>; rel=preload; as=script; nopush","Link: </framework-c8eaec10e45cecbdf79e.js>; rel=preload; as=script; nopush","Link: </app-1af3f4ffdc27ce697953.js>; rel=preload; as=script; nopush","Link: </commons-4229773709d1684763e0.js>; rel=preload; as=script; nopush","Link: </component---src-templates-year-tsx-722f9c28dbeac162c801.js>; rel=preload; as=script; nopush","Link: </page-data/app-data.json>; rel=preload; as=fetch; crossorigin; nopush","Link: </page-data/year/2019년/page-data.json>; rel=preload; as=fetch; crossorigin; nopush"],"/2019-7-national-comm/":["Link: </webpack-runtime-550d9c70ac0e254df46f.js>; rel=preload; as=script; nopush","Link: </framework-c8eaec10e45cecbdf79e.js>; rel=preload; as=script; nopush","Link: </app-1af3f4ffdc27ce697953.js>; rel=preload; as=script; nopush","Link: </commons-4229773709d1684763e0.js>; rel=preload; as=script; nopush","Link: </component---src-templates-blog-post-tsx-cffc0d75d3e219754ee4.js>; rel=preload; as=script; nopush","Link: </page-data/app-data.json>; rel=preload; as=fetch; crossorigin; nopush","Link: </page-data/2019-7-national-comm/page-data.json>; rel=preload; as=fetch; crossorigin; nopush"],"/2018-7-national-comm/":["Link: </webpack-runtime-550d9c70ac0e254df46f.js>; rel=preload; as=script; nopush","Link: </framework-c8eaec10e45cecbdf79e.js>; rel=preload; as=script; nopush","Link: </app-1af3f4ffdc27ce697953.js>; rel=preload; as=script; nopush","Link: </commons-4229773709d1684763e0.js>; rel=preload; as=script; nopush","Link: </component---src-templates-blog-post-tsx-cffc0d75d3e219754ee4.js>; rel=preload; as=script; nopush","Link: </page-data/app-data.json>; rel=preload; as=fetch; crossorigin; nopush","Link: </page-data/2018-7-national-comm/page-data.json>; rel=preload; as=fetch; crossorigin; nopush"],"/year/2018년":["Link: </webpack-runtime-550d9c70ac0e254df46f.js>; rel=preload; as=script; nopush","Link: </framework-c8eaec10e45cecbdf79e.js>; rel=preload; as=script; nopush","Link: </app-1af3f4ffdc27ce697953.js>; rel=preload; as=script; nopush","Link: </commons-4229773709d1684763e0.js>; rel=preload; as=script; nopush","Link: </component---src-templates-year-tsx-722f9c28dbeac162c801.js>; rel=preload; as=script; nopush","Link: </page-data/app-data.json>; rel=preload; as=fetch; crossorigin; nopush","Link: </page-data/year/2018년/page-data.json>; rel=preload; as=fetch; crossorigin; nopush"],"/2017-7-national-comm/":["Link: </webpack-runtime-550d9c70ac0e254df46f.js>; rel=preload; as=script; nopush","Link: </framework-c8eaec10e45cecbdf79e.js>; rel=preload; as=script; nopush","Link: </app-1af3f4ffdc27ce697953.js>; rel=preload; as=script; nopush","Link: </commons-4229773709d1684763e0.js>; rel=preload; as=script; nopush","Link: </component---src-templates-blog-post-tsx-cffc0d75d3e219754ee4.js>; rel=preload; as=script; nopush","Link: </page-data/app-data.json>; rel=preload; as=fetch; crossorigin; nopush","Link: </page-data/2017-7-national-comm/page-data.json>; rel=preload; as=fetch; crossorigin; nopush"],"/year/2017년":["Link: </webpack-runtime-550d9c70ac0e254df46f.js>; rel=preload; as=script; nopush","Link: </framework-c8eaec10e45cecbdf79e.js>; rel=preload; as=script; nopush","Link: </app-1af3f4ffdc27ce697953.js>; rel=preload; as=script; nopush","Link: </commons-4229773709d1684763e0.js>; rel=preload; as=script; nopush","Link: </component---src-templates-year-tsx-722f9c28dbeac162c801.js>; rel=preload; as=script; nopush","Link: </page-data/app-data.json>; rel=preload; as=fetch; crossorigin; nopush","Link: </page-data/year/2017년/page-data.json>; rel=preload; as=fetch; crossorigin; nopush"],"/2021-7-national-ec/":["Link: </webpack-runtime-550d9c70ac0e254df46f.js>; rel=preload; as=script; nopush","Link: </framework-c8eaec10e45cecbdf79e.js>; rel=preload; as=script; nopush","Link: </app-1af3f4ffdc27ce697953.js>; rel=preload; as=script; nopush","Link: </commons-4229773709d1684763e0.js>; rel=preload; as=script; nopush","Link: </component---src-templates-blog-post-tsx-cffc0d75d3e219754ee4.js>; rel=preload; as=script; nopush","Link: </page-data/app-data.json>; rel=preload; as=fetch; crossorigin; nopush","Link: </page-data/2021-7-national-ec/page-data.json>; rel=preload; as=fetch; crossorigin; nopush"]}